megago/__init__.py
megago/constants.py
megago/go_plot.py
megago/heatmap.py
megago/make_go_freq_json.py
megago/megago.py
megago/megago_test.py
megago/metrics.py
megago/precompute_frequency_counts.py
megago/precompute_highest_ic.py
megago/resources/frequency_counts_uniprot.json
megago/resources/go-basic.obo
megago/resources/highest_ic_uniprot.json
megago-1.0.0.2021.4.dist-info/LICENSE
megago-1.0.0.2021.4.dist-info/METADATA
megago-1.0.0.2021.4.dist-info/WHEEL
megago-1.0.0.2021.4.dist-info/entry_points.txt
megago-1.0.0.2021.4.dist-info/top_level.txt
megago-1.0.0.2021.4.dist-info/RECORD
