Metadata-Version: 2.1
Name: megago
Version: 1.0.0.2021.4
Summary: Calculate semantic distance for sets of Gene Ontology terms
Home-page: https://github.com/MEGA-GO/megago
Author: Henning Schiebenhoefer
Author-email: henning.schiebenhoefer@posteo.de
License: LICENSE
Platform: UNKNOWN
Requires-Dist: goatools
Requires-Dist: seaborn
Requires-Dist: progress
